hydrogenline/__init__.py
hydrogenline/dsp.py
hydrogenline/io.py
hydrogenline/plotting.py
hydrogenline/sdr.py
hydrogenline/utils.py
scripts/__init__.py
scripts/capture.py
scripts/waterfall.py
hydrogenline-0.2.dist-info/LICENSE
hydrogenline-0.2.dist-info/METADATA
hydrogenline-0.2.dist-info/WHEEL
hydrogenline-0.2.dist-info/entry_points.txt
hydrogenline-0.2.dist-info/top_level.txt
hydrogenline-0.2.dist-info/RECORD
