Metadata-Version: 2.1
Name: hydrogenline
Version: 0.2
Author-email: ON5VO <contact@on5vo.be>
Project-URL: Homepage, https://github.com/on5vo/hydrogenline
Requires-Python: >=3.10
License-File: LICENSE
Requires-Dist: numpy
Requires-Dist: matplotlib
Requires-Dist: scipy
Requires-Dist: tzlocal
Requires-Dist: pyrtlsdr[lib]
